stale_maccarone/__init__.py
stale_maccarone/caching.mn.py
stale_maccarone/caching.py
stale_maccarone/loader.mn.py
stale_maccarone/loader.py
stale_maccarone/openai.py
stale_maccarone/preprocessor.py
stale_maccarone/scripts/preprocess.mn.py
stale_maccarone/scripts/preprocess.py
stale_maccarone/test/test_caching.py
stale_maccarone/test/test_preprocessor.py
stale_maccarone-0.1.4.dist-info/LICENSE
stale_maccarone-0.1.4.dist-info/METADATA
stale_maccarone-0.1.4.dist-info/WHEEL
stale_maccarone-0.1.4.dist-info/entry_points.txt
stale_maccarone-0.1.4.dist-info/top_level.txt
stale_maccarone-0.1.4.dist-info/RECORD
